odoo/addons/account_payment_batch_oca/README.rst
odoo/addons/account_payment_batch_oca/__init__.py
odoo/addons/account_payment_batch_oca/__manifest__.py
odoo/addons/account_payment_batch_oca/data/mail_template.xml
odoo/addons/account_payment_batch_oca/data/payment_seq.xml
odoo/addons/account_payment_batch_oca/i18n/account_payment_batch_oca.pot
odoo/addons/account_payment_batch_oca/i18n/account_payment_order.pot
odoo/addons/account_payment_batch_oca/i18n/am.po
odoo/addons/account_payment_batch_oca/i18n/ar.po
odoo/addons/account_payment_batch_oca/i18n/ca.po
odoo/addons/account_payment_batch_oca/i18n/ca_ES.po
odoo/addons/account_payment_batch_oca/i18n/cs.po
odoo/addons/account_payment_batch_oca/i18n/da_DK.po
odoo/addons/account_payment_batch_oca/i18n/de.po
odoo/addons/account_payment_batch_oca/i18n/el_GR.po
odoo/addons/account_payment_batch_oca/i18n/es.po
odoo/addons/account_payment_batch_oca/i18n/es_AR.po
odoo/addons/account_payment_batch_oca/i18n/es_CL.po
odoo/addons/account_payment_batch_oca/i18n/es_CR.po
odoo/addons/account_payment_batch_oca/i18n/es_EC.po
odoo/addons/account_payment_batch_oca/i18n/es_ES.po
odoo/addons/account_payment_batch_oca/i18n/es_MX.po
odoo/addons/account_payment_batch_oca/i18n/es_VE.po
odoo/addons/account_payment_batch_oca/i18n/et.po
odoo/addons/account_payment_batch_oca/i18n/fi.po
odoo/addons/account_payment_batch_oca/i18n/fr.po
odoo/addons/account_payment_batch_oca/i18n/fr_FR.po
odoo/addons/account_payment_batch_oca/i18n/gl.po
odoo/addons/account_payment_batch_oca/i18n/hr.po
odoo/addons/account_payment_batch_oca/i18n/it.po
odoo/addons/account_payment_batch_oca/i18n/lt.po
odoo/addons/account_payment_batch_oca/i18n/nb_NO.po
odoo/addons/account_payment_batch_oca/i18n/nl.po
odoo/addons/account_payment_batch_oca/i18n/nl_BE.po
odoo/addons/account_payment_batch_oca/i18n/nl_NL.po
odoo/addons/account_payment_batch_oca/i18n/pl.po
odoo/addons/account_payment_batch_oca/i18n/pt.po
odoo/addons/account_payment_batch_oca/i18n/pt_BR.po
odoo_addon_account_payment_batch_oca-19.0.1.0.0.3.dist-info/METADATA
odoo_addon_account_payment_batch_oca-19.0.1.0.0.3.dist-info/WHEEL
odoo_addon_account_payment_batch_oca-19.0.1.0.0.3.dist-info/top_level.txt
odoo_addon_account_payment_batch_oca-19.0.1.0.0.3.dist-info/RECORD
