Metadata-Version: 2.1
Name: odoo-addon-account_payment_batch_oca
Version: 19.0.1.0.0.3
Requires-Dist: odoo-addon-account_payment_base_oca==19.0.*
Requires-Dist: odoo==19.0.*
Summary: Add payment orders and debit orders
Home-page: https://github.com/OCA/bank-payment-alternative
License: AGPL-3
Author: ACSONE SA/NV, Therp BV, Tecnativa, Akretion, Odoo Community Association (OCA)
Author-email: support@odoo-community.org
Classifier: Programming Language :: Python
Classifier: Framework :: Odoo
Classifier: Framework :: Odoo :: 19.0
Classifier: License :: OSI Approved :: GNU Affero General Public License v3
Classifier: Development Status :: 6 - Mature
